scylla_bridge/__init__.py
scylla_bridge/column.py
scylla_bridge/metaclass.py
scylla_bridge/metadata.py
scylla_bridge/query.py
scylla_bridge/table.py
scylla_bridge/types.py
scylla_bridge-1.1.2.dist-info/METADATA
scylla_bridge-1.1.2.dist-info/WHEEL
scylla_bridge-1.1.2.dist-info/top_level.txt
scylla_bridge-1.1.2.dist-info/RECORD
