Metadata-Version: 2.1
Name: scylla-bridge
Version: 1.1.2
Summary: An ORM for scylladb
Author-email: "Diviyan K." <diviyan@fentech.ai>
Requires-Python: >=3.11
Requires-Dist: loguru >=0.7.2
Requires-Dist: pydantic >=2.5.2
Requires-Dist: scyllaft >=1.6.3
